{"image_path": "/sciclone/data10/zlv/CNN_ObjectDetection/geo_AnimalDetection/dataset/processing_data/clipped/156.tif", "image_name": "156.tif", "annotations": [{"label": "bird", "region": {"minx": 67, "maxy": 23, "maxx": 30, "miny": 47}}, {"label": "bird", "region": {"minx": 159, "maxy": -9, "maxx": 112, "miny": 14}}, {"label": "bird", "region": {"minx": 106, "maxy": 7, "maxx": 67, "miny": 32}}, {"label": "bird", "region": {"minx": 99, "maxy": 34, "maxx": 59, "miny": 57}}, {"label": "bird", "region": {"minx": 147, "maxy": 49, "maxx": 113, "miny": 74}}, {"label": "bird", "region": {"minx": 245, "maxy": 8, "maxx": 201, "miny": 36}}, {"label": "bird", "region": {"minx": 262, "maxy": 66, "maxx": 224, "miny": 86}}, {"label": "bird", "region": {"minx": 211, "maxy": 71, "maxx": 171, "miny": 103}}, {"label": "bird", "region": {"minx": 192, "maxy": 40, "maxx": 150, "miny": 67}}, {"label": "bird", "region": {"minx": 59, "maxy": 71, "maxx": 14, "miny": 92}}, {"label": "bird", "region": {"minx": 79, "maxy": 94, "maxx": 40, "miny": 120}}, {"label": "bird", "region": {"minx": 114, "maxy": 85, "maxx": 75, "miny": 109}}, {"label": "bird", "region": {"minx": 36, "maxy": 109, "maxx": -2, "miny": 127}}, {"label": "bird", "region": {"minx": 26, "maxy": 148, "maxx": -18, "miny": 177}}, {"label": "bird", "region": {"minx": 70, "maxy": 147, "maxx": 25, "miny": 173}}, {"label": "bird", "region": {"minx": 121, "maxy": 133, "maxx": 76, "miny": 158}}, {"label": "bird", "region": {"minx": 162, "maxy": 91, "maxx": 124, "miny": 115}}, {"label": "bird", "region": {"minx": 147, "maxy": 116, "maxx": 109, "miny": 140}}, {"label": "bird", "region": {"minx": 198, "maxy": 111, "maxx": 156, "miny": 131}}, {"label": "bird", "region": {"minx": 225, "maxy": 97, "maxx": 204, "miny": 134}}, {"label": "bird", "region": {"minx": 250, "maxy": 144, "maxx": 211, "miny": 168}}, {"label": "bird", "region": {"minx": 53, "maxy": 195, "maxx": 16, "miny": 213}}, {"label": "bird", "region": {"minx": 81, "maxy": 225, "maxx": 41, "miny": 257}}, {"label": "bird", "region": {"minx": 40, "maxy": 234, "maxx": -1, "miny": 263}}, {"label": "bird", "region": {"minx": 268, "maxy": 196, "maxx": 224, "miny": 231}}, {"label": "bird", "region": {"minx": 180, "maxy": 161, "maxx": 138, "miny": 183}}, {"label": "bird", "region": {"minx": 173, "maxy": 206, "maxx": 130, "miny": 236}}, {"label": "bird", "region": {"minx": 220, "maxy": 203, "maxx": 176, "miny": 233}}, {"label": "bird", "region": {"minx": 241, "maxy": 229, "maxx": 201, "miny": 270}}, {"label": "bird", "region": {"minx": 194, "maxy": 227, "maxx": 152, "miny": 264}}], "width": 256, "height": 256}