{"image_path": "/home/mirandalv/Documents/github/geo_AnimalDetection/dataset/processing_data/clipped/179.tif", "image_name": "179.tif", "annotations": [{"label": "bird", "region": {"minx": -4, "maxy": 61, "maxx": 19, "miny": 102}}, {"label": "bird", "region": {"minx": 1, "maxy": 178, "maxx": 32, "miny": 224}}, {"label": "bird", "region": {"minx": 56, "maxy": 12, "maxx": 78, "miny": 52}}, {"label": "bird", "region": {"minx": 51, "maxy": 47, "maxx": 79, "miny": 83}}, {"label": "bird", "region": {"minx": 32, "maxy": 87, "maxx": 60, "miny": 128}}, {"label": "bird", "region": {"minx": 81, "maxy": 84, "maxx": 97, "miny": 122}}, {"label": "bird", "region": {"minx": 102, "maxy": -6, "maxx": 120, "miny": 34}}, {"label": "bird", "region": {"minx": 116, "maxy": 108, "maxx": 138, "miny": 150}}, {"label": "bird", "region": {"minx": 25, "maxy": 132, "maxx": 45, "miny": 173}}, {"label": "bird", "region": {"minx": 53, "maxy": 168, "maxx": 78, "miny": 213}}, {"label": "bird", "region": {"minx": 79, "maxy": 200, "maxx": 115, "miny": 239}}, {"label": "bird", "region": {"minx": 108, "maxy": 155, "maxx": 129, "miny": 195}}, {"label": "bird", "region": {"minx": 32, "maxy": 213, "maxx": 69, "miny": 256}}, {"label": "bird", "region": {"minx": 180, "maxy": 5, "maxx": 205, "miny": 45}}, {"label": "bird", "region": {"minx": 166, "maxy": 42, "maxx": 191, "miny": 84}}, {"label": "bird", "region": {"minx": 154, "maxy": 100, "maxx": 177, "miny": 141}}, {"label": "bird", "region": {"minx": 151, "maxy": 141, "maxx": 172, "miny": 183}}, {"label": "bird", "region": {"minx": 190, "maxy": 173, "maxx": 215, "miny": 215}}, {"label": "bird", "region": {"minx": 121, "maxy": 229, "maxx": 145, "miny": 270}}, {"label": "bird", "region": {"minx": 167, "maxy": 220, "maxx": 192, "miny": 264}}, {"label": "bird", "region": {"minx": 218, "maxy": 208, "maxx": 243, "miny": 251}}], "width": 256, "height": 256}