{"image_path": "/sciclone/data10/zlv/CNN_ObjectDetection/geo_AnimalDetection/dataset/processing_data/clipped/228.tif", "image_name": "228.tif", "annotations": [{"label": "bird", "region": {"minx": 217, "maxy": -4, "maxx": 241, "miny": 32}}, {"label": "bird", "region": {"minx": 134, "maxy": -15, "maxx": 162, "miny": 25}}, {"label": "bird", "region": {"minx": 174, "maxy": 5, "maxx": 202, "miny": 50}}, {"label": "bird", "region": {"minx": 136, "maxy": 25, "maxx": 162, "miny": 60}}, {"label": "bird", "region": {"minx": 164, "maxy": 45, "maxx": 197, "miny": 83}}, {"label": "bird", "region": {"minx": 208, "maxy": 42, "maxx": 237, "miny": 77}}, {"label": "bird", "region": {"minx": 246, "maxy": 67, "maxx": 263, "miny": 108}}, {"label": "bird", "region": {"minx": 205, "maxy": 83, "maxx": 230, "miny": 121}}, {"label": "bird", "region": {"minx": 155, "maxy": 90, "maxx": 183, "miny": 135}}, {"label": "bird", "region": {"minx": 125, "maxy": 60, "maxx": 156, "miny": 102}}, {"label": "bird", "region": {"minx": 238, "maxy": 113, "maxx": 265, "miny": 158}}, {"label": "bird", "region": {"minx": 194, "maxy": 119, "maxx": 222, "miny": 162}}, {"label": "bird", "region": {"minx": 113, "maxy": 107, "maxx": 143, "miny": 148}}, {"label": "bird", "region": {"minx": 110, "maxy": 151, "maxx": 145, "miny": 196}}, {"label": "bird", "region": {"minx": 159, "maxy": 143, "maxx": 192, "miny": 192}}, {"label": "bird", "region": {"minx": 217, "maxy": 200, "maxx": 248, "miny": 248}}, {"label": "bird", "region": {"minx": 190, "maxy": 207, "maxx": 219, "miny": 255}}, {"label": "bird", "region": {"minx": 145, "maxy": 233, "maxx": 176, "miny": 273}}, {"label": "bird", "region": {"minx": 138, "maxy": 181, "maxx": 168, "miny": 223}}, {"label": "bird", "region": {"minx": 93, "maxy": 201, "maxx": 124, "miny": 245}}, {"label": "bird", "region": {"minx": 74, "maxy": 172, "maxx": 94, "miny": 209}}, {"label": "bird", "region": {"minx": 31, "maxy": 227, "maxx": 58, "miny": 270}}, {"label": "bird", "region": {"minx": 5, "maxy": 233, "maxx": 33, "miny": 271}}, {"label": "bird", "region": {"minx": 48, "maxy": -9, "maxx": 76, "miny": 32}}, {"label": "bird", "region": {"minx": 1, "maxy": 21, "maxx": 34, "miny": 63}}, {"label": "bird", "region": {"minx": 31, "maxy": 42, "maxx": 61, "miny": 83}}, {"label": "bird", "region": {"minx": -10, "maxy": 57, "maxx": 15, "miny": 97}}, {"label": "bird", "region": {"minx": 17, "maxy": 134, "maxx": 39, "miny": 173}}, {"label": "bird", "region": {"minx": 49, "maxy": 127, "maxx": 81, "miny": 169}}, {"label": "bird", "region": {"minx": 87, "maxy": 41, "maxx": 108, "miny": 79}}, {"label": "bird", "region": {"minx": 88, "maxy": -20, "maxx": 110, "miny": 19}}], "width": 256, "height": 256}