{"image_path": "/home/mirandalv/Documents/github/geo_AnimalDetection/dataset/processing_data/clipped/251.tif", "image_name": "251.tif", "annotations": [{"label": "bird", "region": {"xmin": 0, "ymax": 233, "xmax": 33, "ymin": 206}}, {"label": "bird", "region": {"xmin": 0, "ymax": 190, "xmax": 37, "ymin": 162}}, {"label": "bird", "region": {"xmin": 0, "ymax": 111, "xmax": 23, "ymin": 81}}, {"label": "bird", "region": {"xmin": 26, "ymax": 113, "xmax": 71, "ymin": 78}}, {"label": "bird", "region": {"xmin": 18, "ymax": 160, "xmax": 67, "ymin": 127}}, {"label": "bird", "region": {"xmin": 37, "ymax": 247, "xmax": 67, "ymin": 204}}, {"label": "bird", "region": {"xmin": 70, "ymax": 266, "xmax": 102, "ymin": 225}}, {"label": "bird", "region": {"xmin": 159, "ymax": 237, "xmax": 204, "ymin": 206}}, {"label": "bird", "region": {"xmin": 219, "ymax": 243, "xmax": 262, "ymin": 214}}, {"label": "bird", "region": {"xmin": 75, "ymax": 216, "xmax": 123, "ymin": 185}}, {"label": "bird", "region": {"xmin": 82, "ymax": 187, "xmax": 130, "ymin": 158}}, {"label": "bird", "region": {"xmin": 130, "ymax": 219, "xmax": 173, "ymin": 188}}, {"label": "bird", "region": {"xmin": 170, "ymax": 189, "xmax": 209, "ymin": 169}}, {"label": "bird", "region": {"xmin": 200, "ymax": 185, "xmax": 244, "ymin": 163}}, {"label": "bird", "region": {"xmin": 108, "ymax": 144, "xmax": 148, "ymin": 113}}, {"label": "bird", "region": {"xmin": 140, "ymax": 160, "xmax": 184, "ymin": 135}}, {"label": "bird", "region": {"xmin": 195, "ymax": 159, "xmax": 229, "ymin": 124}}, {"label": "bird", "region": {"xmin": 151, "ymax": 108, "xmax": 191, "ymin": 89}}, {"label": "bird", "region": {"xmin": 121, "ymax": 70, "xmax": 160, "ymin": 52}}, {"label": "bird", "region": {"xmin": 56, "ymax": 136, "xmax": 98, "ymin": 106}}, {"label": "bird", "region": {"xmin": 76, "ymax": 92, "xmax": 120, "ymin": 61}}, {"label": "bird", "region": {"xmin": 225, "ymax": 132, "xmax": 270, "ymin": 102}}, {"label": "bird", "region": {"xmin": 173, "ymax": 55, "xmax": 217, "ymin": 27}}, {"label": "bird", "region": {"xmin": 47, "ymax": 62, "xmax": 84, "ymin": 42}}, {"label": "bird", "region": {"xmin": 102, "ymax": 26, "xmax": 145, "ymin": 0}}, {"label": "bird", "region": {"xmin": 152, "ymax": 26, "xmax": 190, "ymin": 1}}, {"label": "bird", "region": {"xmin": 222, "ymax": 33, "xmax": 254, "ymin": 0}}, {"label": "bird", "region": {"xmin": 214, "ymax": 62, "xmax": 252, "ymin": 24}}, {"label": "bird", "region": {"xmin": 182, "ymax": 29, "xmax": 219, "ymin": 0}}, {"label": "bird", "region": {"xmin": 2, "ymax": 49, "xmax": 44, "ymin": 17}}], "width": 256, "height": 256}