{"image_path": "/sciclone/data10/zlv/CNN_ObjectDetection/geo_AnimalDetection/dataset/processing_data/clipped/347.tif", "image_name": "347.tif", "annotations": [{"label": "bird", "region": {"minx": 137, "maxy": 26, "maxx": 164, "miny": 74}}, {"label": "bird", "region": {"minx": 81, "maxy": 86, "maxx": 104, "miny": 126}}, {"label": "bird", "region": {"minx": 124, "maxy": 58, "maxx": 144, "miny": 97}}, {"label": "bird", "region": {"minx": 112, "maxy": 106, "maxx": 144, "miny": 150}}, {"label": "bird", "region": {"minx": 221, "maxy": 139, "maxx": 264, "miny": 187}}], "width": 256, "height": 256}