{"image_path": "/home/mirandalv/Documents/github/geo_AnimalDetection/dataset/processing_data/clipped/482.tif", "image_name": "482.tif", "annotations": [{"label": "bird", "region": {"minx": 2, "maxy": 8, "maxx": 25, "miny": 49}}, {"label": "bird", "region": {"minx": 0, "maxy": 133, "maxx": 28, "miny": 177}}, {"label": "bird", "region": {"minx": -6, "maxy": 189, "maxx": 27, "miny": 235}}, {"label": "bird", "region": {"minx": 41, "maxy": 164, "maxx": 71, "miny": 208}}, {"label": "bird", "region": {"minx": 79, "maxy": 206, "maxx": 107, "miny": 248}}, {"label": "bird", "region": {"minx": 107, "maxy": 224, "maxx": 142, "miny": 273}}, {"label": "bird", "region": {"minx": 45, "maxy": 120, "maxx": 76, "miny": 166}}, {"label": "bird", "region": {"minx": 83, "maxy": 143, "maxx": 116, "miny": 190}}, {"label": "bird", "region": {"minx": 119, "maxy": 184, "maxx": 149, "miny": 227}}, {"label": "bird", "region": {"minx": 153, "maxy": 137, "maxx": 181, "miny": 188}}, {"label": "bird", "region": {"minx": 112, "maxy": 101, "maxx": 141, "miny": 154}}, {"label": "bird", "region": {"minx": 75, "maxy": 61, "maxx": 107, "miny": 105}}, {"label": "bird", "region": {"minx": 39, "maxy": -5, "maxx": 65, "miny": 36}}, {"label": "bird", "region": {"minx": 107, "maxy": 46, "maxx": 138, "miny": 90}}, {"label": "bird", "region": {"minx": 146, "maxy": 83, "maxx": 175, "miny": 132}}, {"label": "bird", "region": {"minx": 182, "maxy": 115, "maxx": 214, "miny": 158}}, {"label": "bird", "region": {"minx": 214, "maxy": 154, "maxx": 247, "miny": 199}}, {"label": "bird", "region": {"minx": 177, "maxy": 176, "maxx": 209, "miny": 218}}, {"label": "bird", "region": {"minx": 169, "maxy": 222, "maxx": 195, "miny": 264}}, {"label": "bird", "region": {"minx": 163, "maxy": 41, "maxx": 193, "miny": 83}}, {"label": "bird", "region": {"minx": 125, "maxy": 4, "maxx": 152, "miny": 47}}], "width": 256, "height": 256}