{"image_path": "/sciclone/data10/zlv/CNN_ObjectDetection/geo_AnimalDetection/dataset/processing_data/clipped/510.tif", "image_name": "510.tif", "annotations": [{"label": "bird", "region": {"minx": 24, "maxy": 226, "maxx": -10, "miny": 261}}, {"label": "bird", "region": {"minx": 65, "maxy": 204, "maxx": 20, "miny": 234}}, {"label": "bird", "region": {"minx": 80, "maxy": 168, "maxx": 34, "miny": 202}}, {"label": "bird", "region": {"minx": 132, "maxy": 166, "maxx": 88, "miny": 196}}, {"label": "bird", "region": {"minx": 113, "maxy": 205, "maxx": 73, "miny": 237}}, {"label": "bird", "region": {"minx": 169, "maxy": 203, "maxx": 128, "miny": 234}}, {"label": "bird", "region": {"minx": 49, "maxy": 100, "maxx": 17, "miny": 135}}, {"label": "bird", "region": {"minx": 47, "maxy": 126, "maxx": 9, "miny": 164}}, {"label": "bird", "region": {"minx": 31, "maxy": 60, "maxx": -8, "miny": 87}}, {"label": "bird", "region": {"minx": 72, "maxy": 49, "maxx": 35, "miny": 77}}, {"label": "bird", "region": {"minx": 48, "maxy": 13, "maxx": 10, "miny": 42}}, {"label": "bird", "region": {"minx": 88, "maxy": 8, "maxx": 50, "miny": 38}}, {"label": "bird", "region": {"minx": 156, "maxy": 3, "maxx": 112, "miny": 38}}, {"label": "bird", "region": {"minx": 129, "maxy": 39, "maxx": 87, "miny": 75}}, {"label": "bird", "region": {"minx": 171, "maxy": 44, "maxx": 132, "miny": 72}}, {"label": "bird", "region": {"minx": 128, "maxy": 83, "maxx": 91, "miny": 111}}, {"label": "bird", "region": {"minx": 228, "maxy": 18, "maxx": 186, "miny": 42}}, {"label": "bird", "region": {"minx": 209, "maxy": 70, "maxx": 167, "miny": 98}}, {"label": "bird", "region": {"minx": 171, "maxy": 82, "maxx": 125, "miny": 111}}, {"label": "bird", "region": {"minx": 277, "maxy": 1, "maxx": 234, "miny": 37}}, {"label": "bird", "region": {"minx": 268, "maxy": 70, "maxx": 225, "miny": 94}}, {"label": "bird", "region": {"minx": 107, "maxy": 111, "maxx": 77, "miny": 146}}, {"label": "bird", "region": {"minx": 146, "maxy": 110, "maxx": 111, "miny": 148}}, {"label": "bird", "region": {"minx": 209, "maxy": 118, "maxx": 169, "miny": 142}}, {"label": "bird", "region": {"minx": 221, "maxy": 139, "maxx": 176, "miny": 167}}, {"label": "bird", "region": {"minx": 241, "maxy": 125, "maxx": 202, "miny": 147}}, {"label": "bird", "region": {"minx": 257, "maxy": 177, "maxx": 210, "miny": 210}}, {"label": "bird", "region": {"minx": 266, "maxy": 134, "maxx": 229, "miny": 172}}, {"label": "bird", "region": {"minx": 237, "maxy": 230, "maxx": 198, "miny": 252}}], "width": 256, "height": 256}